dl_comm/__init__.py
dl_comm/dl_comm_main.py
dl_comm/analysis/__init__.py
dl_comm/analysis/bandwidth.py
dl_comm/analysis/ccl_parser.py
dl_comm/analysis/correctness.py
dl_comm/comm/__init__.py
dl_comm/comm/collectives.py
dl_comm/comm/comm_setup.py
dl_comm/config/__init__.py
dl_comm/config/config_spec.json
dl_comm/config/mpi_utils.py
dl_comm/config/setup_algorithms.py
dl_comm/config/system_info.py
dl_comm/config/validation.py
dl_comm/timer/__init__.py
dl_comm/timer/timer.py
dl_comm/utils/__init__.py
dl_comm/utils/utility.py
dlcomm-0.3.5.dist-info/METADATA
dlcomm-0.3.5.dist-info/WHEEL
dlcomm-0.3.5.dist-info/entry_points.txt
dlcomm-0.3.5.dist-info/top_level.txt
dlcomm-0.3.5.dist-info/RECORD
