Metadata-Version: 2.4
Name: dlcomm
Version: 0.3.5
Summary: Distributed GPU Communication Benchmarking Framework for Deep Learning
Author-email: Musa Cim <musaoguzhancim@gmail.com>, Kaushik Velusamy <kaushikvelusamy@gmail.com>
Project-URL: Homepage, https://github.com/argonne-lcf/DLcomm_benchmark
Project-URL: Documentation, https://github.com/argonne-lcf/DLcomm_benchmark
Project-URL: Repository, https://github.com/argonne-lcf/DLcomm_benchmark
Project-URL: Bug Tracker, https://github.com/argonne-lcf/DLcomm_benchmark/issues
Keywords: deep-learning,gpu,communication,benchmark,mpi,distributed,pytorch,ccl
Classifier: Development Status :: 3 - Alpha
Classifier: Intended Audience :: Developers
Classifier: Intended Audience :: Science/Research
Classifier: License :: OSI Approved :: MIT License
Classifier: Programming Language :: Python :: 3
Classifier: Programming Language :: Python :: 3.8
Classifier: Programming Language :: Python :: 3.9
Classifier: Programming Language :: Python :: 3.10
Classifier: Programming Language :: Python :: 3.11
Classifier: Topic :: Scientific/Engineering :: Artificial Intelligence
Classifier: Topic :: System :: Distributed Computing
Classifier: Topic :: System :: Benchmark
Classifier: Operating System :: POSIX :: Linux
Requires-Python: >=3.8
Requires-Dist: mpi4py>=3.1.0
Requires-Dist: hydra-core>=1.1.0
Requires-Dist: omegaconf>=2.1.0
Requires-Dist: pytz>=2021.1
Requires-Dist: torch>=1.12.0
Provides-Extra: intel
Requires-Dist: intel-extension-for-pytorch; extra == "intel"
Requires-Dist: oneccl-bindings-for-pytorch; extra == "intel"
Provides-Extra: dev
Requires-Dist: pytest>=6.0; extra == "dev"
Requires-Dist: black>=22.0; extra == "dev"
Requires-Dist: flake8>=4.0; extra == "dev"
Requires-Dist: mypy>=0.950; extra == "dev"
